CHANGELOG.txt
LICENCE.txt
MANIFEST.in
README.txt
__init__.py
setup.py
gtheeg/__init__.py
gtheeg/preprocessing/__init__.py
gtheeg/preprocessing/preprocessing.py
gtheeg/preprocessing/features_extraction/__init__.py
gtheeg/preprocessing/features_extraction/features_extraction.py
gtheeg/utilities/__init__.py
gtheeg/utilities/utilities.py
gtheeg/visualization/visualization.py
gtheeglib.egg-info/PKG-INFO
gtheeglib.egg-info/SOURCES.txt
gtheeglib.egg-info/dependency_links.txt
gtheeglib.egg-info/requires.txt
gtheeglib.egg-info/top_level.txt